avclass/__init__.py
avclass/avclass_common.py
avclass/evaluate_clustering.py
avclass/data/default.aliases
avclass/data/default.generics
avclass/data/malheurReference_gt.tsv
avclass/data/malheurReference_lb.json
avclass-0.1.dist-info/LICENSE
avclass-0.1.dist-info/METADATA
avclass-0.1.dist-info/WHEEL
avclass-0.1.dist-info/top_level.txt
avclass-0.1.dist-info/RECORD
