Metadata-Version: 2.1
Name: avclass
Version: 0.1
Summary: Avclass labeler
Home-page: https://github.com/malicialab/avclass
Author: malicialab
Author-email: scattell@gmail.com
License: MIT
Platform: UNKNOWN
